satnogs_client-2.1.1.dist-info/licenses/LICENSE
satnogsclient/__init__.py
satnogsclient/__main__.py
satnogsclient/_version.py
satnogsclient/artifacts.py
satnogsclient/config.py
satnogsclient/rig.py
satnogsclient/rotator.py
satnogsclient/settings.py
satnogsclient/waterfall.py
satnogsclient/locator/__init__.py
satnogsclient/locator/locator.py
satnogsclient/observer/__init__.py
satnogsclient/observer/observer.py
satnogsclient/observer/obsever_test.py
satnogsclient/observer/orbital.py
satnogsclient/observer/worker.py
satnogsclient/radio/__init__.py
satnogsclient/radio/flowgraphs.py
satnogsclient/radio/grsat.py
satnogsclient/scheduler/__init__.py
satnogsclient/scheduler/tasks.py
satnogs_client-2.1.1.dist-info/METADATA
satnogs_client-2.1.1.dist-info/WHEEL
satnogs_client-2.1.1.dist-info/entry_points.txt
satnogs_client-2.1.1.dist-info/top_level.txt
satnogs_client-2.1.1.dist-info/RECORD
