Metadata-Version: 2.4
Name: satnogs-client
Version: 2.1.1
Summary: SatNOGS Client
Home-page: https://gitlab.com/librespacefoundation/satnogs/satnogs-client
Author: SatNOGS project
Author-email: dev@satnogs.org
License: AGPLv3
Classifier: Development Status :: 4 - Beta
Classifier: Environment :: Console
Classifier: Intended Audience :: Telecommunications Industry
Classifier: Intended Audience :: Science/Research
Classifier: License :: OSI Approved :: GNU Affero General Public License v3
Classifier: Operating System :: POSIX :: Linux
Classifier: Programming Language :: Python :: 3.6
Classifier: Topic :: Communications :: Ham Radio
License-File: LICENSE
Requires-Dist: APScheduler~=3.9.0
Requires-Dist: python-dotenv~=0.21.0
Requires-Dist: requests~=2.28.0
Requires-Dist: validators~=0.20.0
Requires-Dist: python-dateutil~=2.8.0
Requires-Dist: ephem~=4.1.5.0
Requires-Dist: pytz
Requires-Dist: numpy~=1.26.0
Requires-Dist: h5py~=3.13.0
Requires-Dist: matplotlib~=3.8.0
Requires-Dist: sentry-sdk~=1.9.0
Requires-Dist: versioneer~=0.28.0
Provides-Extra: dev
Requires-Dist: build~=0.10.0; extra == "dev"
Requires-Dist: flake8-quotes~=3.3.0; extra == "dev"
Requires-Dist: flake8~=4.0.0; extra == "dev"
Requires-Dist: isort~=5.10.0; extra == "dev"
Requires-Dist: pylint~=3.3.6; extra == "dev"
Requires-Dist: pytest~=7.1.0; extra == "dev"
Requires-Dist: pytest-xdist~=3.3.0; extra == "dev"
Requires-Dist: pytest-forked~=1.6.0; extra == "dev"
Requires-Dist: robotframework-httpctrl~=0.3.0; extra == "dev"
Requires-Dist: robotframework-tidy~=2.6.0; extra == "dev"
Requires-Dist: robotframework~=5.0.0; extra == "dev"
Requires-Dist: sphinx_rtd_theme~=1.2.0; extra == "dev"
Requires-Dist: tox~=4.5.0; extra == "dev"
Requires-Dist: twine~=6.1.0; extra == "dev"
Requires-Dist: yapf~=0.40.0; extra == "dev"
Dynamic: license-file
